skrample/__init__.py
skrample/common.py
skrample/diffusers.py
skrample/pytorch/__init__.py
skrample/pytorch/noise.py
skrample/sampling.py
skrample/scheduling.py
skrample-0.5.1.dist-info/WHEEL
skrample-0.5.1.dist-info/METADATA
skrample-0.5.1.dist-info/RECORD
